{
  "project_info": {
    "project_number": "757718542396",
    "project_id": "tow-factory",
    "storage_bucket": "tow-factory.firebasestorage.app"
  },
  "client": [
    {
      "client_info": {
        "mobilesdk_app_id": "1:757718542396:android:5587c141e48df103667b39",
        "android_client_info": {
          "package_name": "com.towfactory.driverapp"
        }
      },
      "oauth_client": [],
      "api_key": [
        {
          "current_key": "AIzaSyBOWxG6ywIkNFU351of8s-t_B46kR_3f88"
        }
      ],
      "services": {
        "appinvite_service": {
          "other_platform_oauth_client": []
        }
      }
    }
  ],
  "configuration_version": "1"
}